tableextractions/__init__.py
tableextractions/pdf_table_extractions.py
tableextractions/utils.py
tableextractions-0.1.dist-info/METADATA
tableextractions-0.1.dist-info/WHEEL
tableextractions-0.1.dist-info/top_level.txt
tableextractions-0.1.dist-info/RECORD
