Metadata-Version: 2.1
Name: tableextractions
Version: 0.1
Summary: Table extractions for COSMOS
Home-page: https://github.com/UW-COSMOS/Cosmos/tree/v0.2.0/services/table_extractions
Author: Sahil Verma
Author-email: UNKNOWN
License: Apache
Platform: UNKNOWN
